lmconf/__init__.py
lmconf/_version.py
lmconf/config.py
lmconf/env_cache_settings.py
lmconf/py.typed
lmconf/settings.py
lmconf/llm_configs/azure_openai.py
lmconf/llm_configs/tongyi.py
lmconf-0.0.5.dist-info/METADATA
lmconf-0.0.5.dist-info/WHEEL
lmconf-0.0.5.dist-info/top_level.txt
lmconf-0.0.5.dist-info/RECORD
