Metadata-Version: 2.1
Name: lmconf
Version: 0.0.5
Author-email: huaxlin <huaxlin33@gmail.com>
Project-URL: Home, https://github.com/huaxlin/lmconf
Requires-Python: >=3.8
Requires-Dist: pydantic >=2
Provides-Extra: demo
Requires-Dist: pydantic-settings ; extra == 'demo'
Provides-Extra: dev
Requires-Dist: black ; extra == 'dev'
Requires-Dist: flake8 ; extra == 'dev'
Requires-Dist: isort ; extra == 'dev'
Requires-Dist: mypy ; extra == 'dev'
Requires-Dist: rich ; extra == 'dev'
Provides-Extra: langchain
Requires-Dist: langchain >0.2 ; extra == 'langchain'
Requires-Dist: langchain-community ; extra == 'langchain'
Requires-Dist: langchain-openai ; extra == 'langchain'
Provides-Extra: test
Requires-Dist: pytest ; extra == 'test'
Requires-Dist: requests-mock ; extra == 'test'
Requires-Dist: pytest-httpx ; extra == 'test'
